{
  "name": "classes",
  "base": "PersistedModel",
  "idInjection": true,
  "options": {
    "validateUpsert": true
  },
  "properties": {
    "class": {
      "type": "string",
      "required": true
    },
    "length": {
      "type": "string",
      "required": true
    },
    "fee": {
      "type": "string",
      "required": true
    },
    "date": {
      "type": "string",
      "required": true
    },
    "time": {
      "type": "string"
    }
  },
  "validations": [],
  "relations": {},
  "acls": [],
  "methods": {}
}
